{
	"textures": {
		"0": "mineraft:mr/structures/smelteries/simple_smelter",
		"particle": "mineraft:mr/structures/smelteries/simple_smelter"
	},
	"elements": [
		{
			"from": [-1.73218, 1, 4.18686],
			"to": [1.26782, 6, 10.18686],
			"rotation": {"x": 180, "y": -45, "z": 180, "origin": [7.9771, 9, 8.08969]},
			"faces": {
				"north": {"uv": [0, 1.66667, 1, 3.33333], "texture": "#0"},
				"east": {"uv": [0, 1.66667, 2, 3.33333], "texture": "#0"},
				"south": {"uv": [1.66667, 1.66667, 2.66667, 3.33333], "texture": "#0"},
				"west": {"uv": [0, 1.66667, 2, 3.33334], "texture": "#0"},
				"up": {"uv": [12, 1.33333, 10, 0.33333], "rotation": 90, "texture": "#0"},
				"down": {"uv": [10, 1.33334, 12, 0.33334], "rotation": 90, "texture": "#0"}
			}
		},
		{
			"from": [-1.61259, 1, 4.06679],
			"to": [1.38741, 6, 12.06679],
			"rotation": {"x": 180, "y": 0, "z": 180, "origin": [7.9771, 9, 8.08969]},
			"faces": {
				"north": {"uv": [0, 0, 1, 1.66667], "texture": "#0"},
				"east": {"uv": [0, 0, 2.66667, 1.66667], "texture": "#0"},
				"south": {"uv": [1.66667, 0, 2.66667, 1.66667], "texture": "#0"},
				"west": {"uv": [0, 0, 2.66667, 1.66667], "texture": "#0"},
				"up": {"uv": [10, 1.33334, 12.66667, 0.33334], "rotation": 90, "texture": "#0"},
				"down": {"uv": [12.66667, 1.33333, 10, 0.33333], "rotation": 90, "texture": "#0"}
			}
		},
		{
			"from": [-1.58519, 1, 4.03229],
			"to": [1.41481, 6, 12.03229],
			"rotation": {"x": 180, "y": 45, "z": 180, "origin": [7.9771, 9, 8.08969]},
			"faces": {
				"north": {"uv": [0, 1.66667, 1, 3.33333], "texture": "#0"},
				"east": {"uv": [0, 1.66667, 2.66667, 3.33333], "texture": "#0"},
				"south": {"uv": [1.66667, 1.66667, 2.66667, 3.33333], "texture": "#0"},
				"west": {"uv": [0, 1.66667, 2.66667, 3.33334], "texture": "#0"},
				"up": {"uv": [2.66667, 3.33333, 0, 2.33333], "rotation": 90, "texture": "#0"},
				"down": {"uv": [12.66667, 1.33333, 10, 0.33333], "rotation": 90, "texture": "#0"}
			}
		},
		{
			"from": [-1.85534, 1, 5.76213],
			"to": [1.14466, 6, 11.76213],
			"rotation": {"angle": -45, "axis": "y", "origin": [7.9771, 9, 8.08969]},
			"faces": {
				"north": {"uv": [0, 0, 1, 1.66667], "texture": "#0"},
				"east": {"uv": [0, 0, 2, 1.66667], "texture": "#0"},
				"south": {"uv": [1.66667, 0, 2.66667, 1.66667], "texture": "#0"},
				"west": {"uv": [0, 0, 2, 1.66667], "texture": "#0"},
				"up": {"uv": [2, 1.66667, 0, 0.66667], "rotation": 90, "texture": "#0"},
				"down": {"uv": [12, 1.33334, 10, 0.33334], "rotation": 90, "texture": "#0"}
			}
		},
		{
			"from": [-1.6388, 1, 4.09347],
			"to": [1.3612, 6, 12.09347],
			"rotation": {"angle": 45, "axis": "y", "origin": [7.9771, 9, 8.08969]},
			"faces": {
				"north": {"uv": [0, 0, 1, 1.66667], "texture": "#0"},
				"east": {"uv": [0, 0, 2.66667, 1.66667], "texture": "#0"},
				"south": {"uv": [1.66667, 0, 2.66667, 1.66667], "texture": "#0"},
				"west": {"uv": [0, 0, 2.66667, 1.66667], "texture": "#0"},
				"up": {"uv": [2.66667, 1.66667, 0, 0.66667], "rotation": 90, "texture": "#0"},
				"down": {"uv": [12.66667, 1.33333, 10, 0.33333], "rotation": 90, "texture": "#0"}
			}
		},
		{
			"from": [-1.51439, 1, 4.10355],
			"to": [1.48561, 6, 12.10355],
			"rotation": {"x": 0, "y": 90, "z": 0, "origin": [7.9771, 9, 8.08969]},
			"faces": {
				"north": {"uv": [0, 1.66667, 1, 3.33333], "texture": "#0"},
				"east": {"uv": [0, 1.66667, 2.66667, 3.33333], "texture": "#0"},
				"south": {"uv": [1.66667, 1.66667, 2.66667, 3.33333], "texture": "#0"},
				"west": {"uv": [0, 1.66667, 2.66667, 3.33334], "texture": "#0"},
				"up": {"uv": [0, 3.33333, 2.66667, 2.33333], "rotation": 90, "texture": "#0"},
				"down": {"uv": [12.66667, 1.33333, 10, 0.33333], "rotation": 90, "texture": "#0"}
			}
		},
		{
			"from": [-1.61259, 1, 3.93473],
			"to": [1.38741, 6, 11.93473],
			"rotation": {"angle": 0, "axis": "y", "origin": [7.9771, 9, 8.08969]},
			"faces": {
				"north": {"uv": [0, 0, 1, 1.66667], "texture": "#0"},
				"east": {"uv": [0, 0, 2.66667, 1.66667], "texture": "#0"},
				"south": {"uv": [1.66667, 0, 2.66667, 1.66667], "texture": "#0"},
				"west": {"uv": [0, 0, 2.66667, 1.66667], "texture": "#0"},
				"up": {"uv": [0, 1.66667, 2.66667, 0.66667], "rotation": 90, "texture": "#0"},
				"down": {"uv": [12.66667, 1.33333, 10, 0.33333], "rotation": 90, "texture": "#0"}
			}
		},
		{
			"from": [-1.60888, 6, 4.2228],
			"to": [1.39112, 11, 12.2228],
			"rotation": {"x": 180, "y": 12.5, "z": 180, "origin": [7.9771, 9, 8.08969]},
			"faces": {
				"north": {"uv": [0, 0, 1, 1.66667], "texture": "#0"},
				"south": {"uv": [1.66667, 0, 2.66667, 1.66667], "texture": "#0"},
				"west": {"uv": [0, 0, 2.66667, 1.66667], "texture": "#0"},
				"up": {"uv": [0, 1.66667, 2.66667, 0.66667], "rotation": 90, "texture": "#0"},
				"down": {"uv": [12.66667, 1.33334, 10, 0.33334], "rotation": 90, "texture": "#0"}
			}
		},
		{
			"from": [-1.49998, 6, 4.00502],
			"to": [1.50002, 11, 12.00502],
			"rotation": {"x": 180, "y": 57.5, "z": 180, "origin": [7.9771, 9, 8.08969]},
			"faces": {
				"north": {"uv": [0, 0, 1, 1.66667], "texture": "#0"},
				"south": {"uv": [1.66667, 0, 2.66667, 1.66667], "texture": "#0"},
				"west": {"uv": [0, 0, 2.66667, 1.66667], "texture": "#0"},
				"up": {"uv": [2.66667, 1.66667, 0, 0.66667], "rotation": 90, "texture": "#0"},
				"down": {"uv": [12.66667, 1.33334, 10, 0.33334], "rotation": 90, "texture": "#0"}
			}
		},
		{
			"from": [-1.54925, 6, 3.90898],
			"to": [1.45075, 11, 11.90898],
			"rotation": {"x": 0, "y": 77.5, "z": 0, "origin": [7.9771, 9, 8.08969]},
			"faces": {
				"north": {"uv": [0, 0, 1, 1.66667], "texture": "#0"},
				"south": {"uv": [1.66667, 0, 2.66667, 1.66667], "texture": "#0"},
				"west": {"uv": [0, 0, 2.66667, 1.66667], "texture": "#0"},
				"up": {"uv": [0, 1.66667, 2.66667, 0.66667], "rotation": 90, "texture": "#0"},
				"down": {"uv": [12.66667, 1.33334, 10, 0.33334], "rotation": 90, "texture": "#0"}
			}
		},
		{
			"from": [-1.57616, 6, 3.99095],
			"to": [1.42384, 11, 11.99095],
			"rotation": {"angle": 32.5, "axis": "y", "origin": [7.9771, 9, 8.08969]},
			"faces": {
				"north": {"uv": [0, 1.66667, 1, 3.33333], "texture": "#0"},
				"south": {"uv": [1.66667, 1.66667, 2.66667, 3.33333], "texture": "#0"},
				"west": {"uv": [0, 1.66667, 2.66667, 3.33334], "texture": "#0"},
				"up": {"uv": [2.66667, 3.33333, 0, 2.33333], "rotation": 90, "texture": "#0"},
				"down": {"uv": [12.66667, 1.33334, 10, 0.33334], "rotation": 90, "texture": "#0"}
			}
		},
		{
			"from": [14.67384, 6, 3.99095],
			"to": [17.67384, 11, 11.99095],
			"rotation": {"angle": 32.5, "axis": "y", "origin": [7.9771, 9, 8.08969]},
			"faces": {
				"north": {"uv": [0, 1.66667, 1, 3.33333], "texture": "#0"},
				"east": {"uv": [0, 1.66667, 2.66667, 3.33333], "texture": "#0"},
				"south": {"uv": [1.66667, 1.66667, 2.66667, 3.33333], "texture": "#0"},
				"west": {"uv": [0, 1.66667, 2.66667, 3.33333], "texture": "#0"},
				"up": {"uv": [0, 3.33333, 2.66667, 2.33333], "rotation": 90, "texture": "#0"},
				"down": {"uv": [12.66667, 1.33334, 10, 0.33334], "rotation": 90, "texture": "#0"}
			}
		},
		{
			"from": [-1.72519, 6, 7.99651],
			"to": [1.27481, 11, 11.99651],
			"rotation": {"x": 0, "y": -57.5, "z": 0, "origin": [7.9771, 9, 8.08969]},
			"faces": {
				"north": {"uv": [0, 1.66667, 1, 3.33334], "texture": "#0"},
				"south": {"uv": [1.66667, 1.66667, 2.66667, 3.33334], "texture": "#0"},
				"west": {"uv": [1.33333, 1.66667, 2.66667, 3.33334], "texture": "#0"},
				"up": {"uv": [1.33333, 3.33333, 0, 2.33333], "rotation": 90, "texture": "#0"},
				"down": {"uv": [11.33333, 1.33334, 10, 0.33334], "rotation": 90, "texture": "#0"}
			}
		},
		{
			"from": [-1.72519, 8, 3.99651],
			"to": [1.27481, 11, 7.99651],
			"rotation": {"x": 0, "y": -57.5, "z": 0, "origin": [7.9771, 9, 8.08969]},
			"faces": {
				"north": {"uv": [0, 1.66667, 1, 2.66667], "texture": "#0"},
				"south": {"uv": [2.33334, 1.66667, 3.33334, 2.66667], "texture": "#0"},
				"west": {"uv": [0, 1.66667, 1.33333, 2.66667], "texture": "#0"},
				"up": {"uv": [1.33333, 3.33333, 0, 2.33333], "rotation": 90, "texture": "#0"},
				"down": {"uv": [11.33333, 1.33334, 10, 0.33334], "rotation": 90, "texture": "#0"}
			}
		},
		{
			"from": [-1.76211, 6, 4.05753],
			"to": [1.23789, 11, 12.05753],
			"rotation": {"angle": -12.5, "axis": "y", "origin": [7.9771, 9, 8.08969]},
			"faces": {
				"north": {"uv": [0, 0, 1, 1.66667], "texture": "#0"},
				"south": {"uv": [1.66667, 0, 2.66667, 1.66667], "texture": "#0"},
				"west": {"uv": [0, 0, 2.66667, 1.66667], "texture": "#0"},
				"up": {"uv": [0, 1.66667, 2.66667, 0.66667], "rotation": 90, "texture": "#0"},
				"down": {"uv": [12.66667, 1.33334, 10, 0.33334], "rotation": 90, "texture": "#0"}
			}
		},
		{
			"from": [-1.71451, 8, 4.06221],
			"to": [1.28549, 11, 12.06221],
			"rotation": {"x": 180, "y": -77.5, "z": 180, "origin": [7.9771, 9, 8.08969]},
			"faces": {
				"north": {"uv": [0, 0, 1, 1], "texture": "#0"},
				"south": {"uv": [1.66667, 0, 2.66667, 1], "texture": "#0"},
				"west": {"uv": [0, 0, 2.66667, 1], "texture": "#0"},
				"up": {"uv": [0, 0.66667, 2.66667, 1.66667], "rotation": 90, "texture": "#0"},
				"down": {"uv": [12.66667, 1.33333, 10, 0.33333], "rotation": 90, "texture": "#0"}
			}
		},
		{
			"from": [-1.5957, 11, 4.20824],
			"to": [3.4043, 18, 12.20824],
			"rotation": {"x": 180, "y": 22.5, "z": 180, "origin": [7.9771, 9, 8.08969]},
			"faces": {
				"north": {"uv": [0, 5.33333, 1.66667, 7.66667], "texture": "#0"},
				"south": {"uv": [1, 5.33333, 2.66667, 7.66667], "texture": "#0"},
				"west": {"uv": [0, 5.33333, 2.66667, 7.66666], "texture": "#0"},
				"up": {"uv": [2.66667, 7.66667, 0, 6], "rotation": 90, "texture": "#0"},
				"down": {"uv": [12, 1.33334, 10, 0.33334], "rotation": 90, "texture": "#0"}
			}
		},
		{
			"from": [-1.50096, 11, 3.9854],
			"to": [3.49904, 17, 11.9854],
			"rotation": {"x": 180, "y": 67.5, "z": 180, "origin": [7.9771, 9, 8.08969]},
			"faces": {
				"north": {"uv": [0, 3.33333, 1.66667, 5.33333], "texture": "#0"},
				"south": {"uv": [0, 3.33333, 1.66667, 5.33333], "texture": "#0"},
				"west": {"uv": [0, 3.33333, 2.66667, 5.33333], "texture": "#0"},
				"up": {"uv": [2.66667, 5, 0, 3.33333], "rotation": 90, "texture": "#0"},
				"down": {"uv": [12, 1.33334, 10, 0.33334], "rotation": 90, "texture": "#0"}
			}
		},
		{
			"from": [-1.56381, 11, 3.8958],
			"to": [3.43619, 18, 11.8958],
			"rotation": {"x": 0, "y": 67.5, "z": 0, "origin": [7.9771, 9, 8.08969]},
			"faces": {
				"north": {"uv": [0, 5.33333, 1.66667, 7.66667], "texture": "#0"},
				"south": {"uv": [1, 5.33333, 2.66667, 7.66667], "texture": "#0"},
				"west": {"uv": [0, 5.33333, 2.66667, 7.66666], "texture": "#0"},
				"up": {"uv": [2.66667, 7.66667, 0, 6], "rotation": 90, "texture": "#0"},
				"down": {"uv": [12, 1.33334, 10, 0.33334], "rotation": 90, "texture": "#0"}
			}
		},
		{
			"from": [-1.59578, 11, 3.99192],
			"to": [3.40422, 17, 11.99192],
			"rotation": {"angle": 22.5, "axis": "y", "origin": [7.9771, 9, 8.08969]},
			"faces": {
				"north": {"uv": [0, 3.33333, 1.66667, 5.33333], "texture": "#0"},
				"south": {"uv": [0, 3.33333, 1.66667, 5.33333], "texture": "#0"},
				"west": {"uv": [0, 3.33333, 2.66667, 5.33333], "texture": "#0"},
				"up": {"uv": [2.66667, 5, 0, 3.33333], "rotation": 90, "texture": "#0"},
				"down": {"uv": [12, 1.33334, 10, 0.33334], "rotation": 90, "texture": "#0"}
			}
		},
		{
			"from": [12.65422, 11, 3.99192],
			"to": [17.65422, 17, 11.99192],
			"rotation": {"angle": 22.5, "axis": "y", "origin": [7.9771, 9, 8.08969]},
			"faces": {
				"north": {"uv": [0, 3.33333, 1.66667, 5.33333], "texture": "#0"},
				"east": {"uv": [0, 3.33333, 2.66667, 5.33333], "texture": "#0"},
				"south": {"uv": [0, 3.33333, 1.66667, 5.33333], "texture": "#0"},
				"up": {"uv": [2.66667, 5, 0, 3.33333], "rotation": 90, "texture": "#0"},
				"down": {"uv": [12, 1.33334, 10, 0.33334], "rotation": 90, "texture": "#0"}
			}
		},
		{
			"from": [-1.72422, 11, 4.01613],
			"to": [3.27578, 17, 12.01613],
			"rotation": {"x": 0, "y": -67.5, "z": 0, "origin": [7.9771, 9, 8.08969]},
			"faces": {
				"north": {"uv": [0, 3.33333, 1.66667, 5.33333], "texture": "#0"},
				"south": {"uv": [0, 3.33333, 1.66667, 5.33333], "texture": "#0"},
				"west": {"uv": [0, 3.33333, 2.66667, 5.33333], "texture": "#0"},
				"up": {"uv": [2.66667, 5, 0, 3.33333], "rotation": 90, "texture": "#0"},
				"down": {"uv": [12.66667, 2, 10, 0.33334], "rotation": 90, "texture": "#0"}
			}
		},
		{
			"from": [-1.77529, 11, 4.07209],
			"to": [3.22471, 16, 12.07209],
			"rotation": {"angle": -22.5, "axis": "y", "origin": [7.9771, 9, 8.08969]},
			"faces": {
				"north": {"uv": [0, 1.66667, 1.66667, 3.33333], "texture": "#0"},
				"south": {"uv": [1.66667, 1.66667, 3.33333, 3.33333], "texture": "#0"},
				"west": {"uv": [0, 1.66667, 2.66667, 3.33334], "texture": "#0"},
				"up": {"uv": [2.66667, 3.33333, 0, 1.66667], "rotation": 90, "texture": "#0"},
				"down": {"uv": [12, 1.33334, 10, 0.33334], "rotation": 90, "texture": "#0"}
			}
		},
		{
			"from": [-1.69995, 11, 4.07539],
			"to": [3.30005, 16, 12.07539],
			"rotation": {"x": 180, "y": -67.5, "z": 180, "origin": [7.9771, 9, 8.08969]},
			"faces": {
				"north": {"uv": [0, 0, 1.66667, 1.66667], "texture": "#0"},
				"south": {"uv": [1.66667, 0, 3.33333, 1.66667], "texture": "#0"},
				"west": {"uv": [0, 0, 2.66667, 1.66667], "texture": "#0"},
				"up": {"uv": [2.66667, 1.66667, 0, 0], "rotation": 90, "texture": "#0"},
				"down": {"uv": [12.66667, 2, 10, 0.33334], "rotation": 90, "texture": "#0"}
			}
		},
		{
			"from": [2.5, 6, 3],
			"to": [12.5, 19, 13],
			"rotation": {"x": 0, "y": -90, "z": 0, "origin": [7.9771, 9, 8.08969]},
			"faces": {
				"north": {"uv": [0, 1.66667, 3.33333, 6], "texture": "#0"},
				"east": {"uv": [0, 1.66667, 3.33333, 6], "texture": "#0"},
				"south": {"uv": [0, 1.66667, 3.33333, 6], "texture": "#0"},
				"west": {"uv": [0, 1.66667, 3.33333, 6], "texture": "#0"},
				"up": {"uv": [3.33333, 6.66667, 6.66667, 10], "texture": "#0"},
				"down": {"uv": [3.33333, 3.33333, 6.66667, 6.66666], "texture": "#0"}
			}
		},
		{
			"from": [-2, 0, -2],
			"to": [18, 1, 18],
			"faces": {
				"north": {"uv": [9.33333, 9.33333, 16, 9.66667], "texture": "#0"},
				"east": {"uv": [9.33333, 9.33333, 16, 9.66667], "texture": "#0"},
				"south": {"uv": [9.33333, 9.33333, 16, 9.66667], "texture": "#0"},
				"west": {"uv": [9.33333, 9.33333, 16, 9.66667], "texture": "#0"},
				"up": {"uv": [9.33333, 9.33333, 16, 16], "texture": "#0"},
				"down": {"uv": [9.33333, 9.33333, 16, 16], "texture": "#0"}
			}
		}
	]
}